algorithms/__init__.py
algorithms/base_algorithm.py
algorithms/exact_set.py
algorithms/fast_dp.py
algorithms/fast_recursive.py
algorithms/fast_recursive_dual.py
algorithms/monte_carlo.py
schemas/input_schema.py
schemas/output_schema.py
shapley_bankruptcy/__init__.py
shapley_bankruptcy/algorithms/__init__.py
shapley_bankruptcy/algorithms/base_algorithm.py
shapley_bankruptcy/algorithms/dynamic_programming.py
shapley_bankruptcy/algorithms/exact.py
shapley_bankruptcy/algorithms/exact_set.py
shapley_bankruptcy/algorithms/fast_dp.py
shapley_bankruptcy/algorithms/fast_recursive.py
shapley_bankruptcy/algorithms/fast_recursive_dual.py
shapley_bankruptcy/algorithms/monte_carlo.py
shapley_bankruptcy/algorithms/recursive.py
shapley_bankruptcy/algorithms/recursive_dual.py
shapley_bankruptcy/schemas/__init__.py
shapley_bankruptcy/schemas/input_schema.py
shapley_bankruptcy/schemas/output_schema.py
shapley_bankruptcy-0.1.4.dist-info/licenses/LICENSE
shapley_bankruptcy-0.1.4.dist-info/METADATA
shapley_bankruptcy-0.1.4.dist-info/WHEEL
shapley_bankruptcy-0.1.4.dist-info/top_level.txt
shapley_bankruptcy-0.1.4.dist-info/RECORD
