Metadata-Version: 2.4
Name: shapley-bankruptcy
Version: 0.1.4
Summary: Algorithms for computing the Shapley value in bankruptcy games
Author-email: Shunta Yamazaki <shuntaweb@gmail.com>
Requires-Python: >=3.11
License-File: LICENSE
Requires-Dist: numpy<3.0.0,>=2.3.5
Requires-Dist: pydantic<3.0.0,>=2.12.4
Dynamic: license-file
